{
  "root": {
    "ALPHABET_SIZE": 26,
    "children": [
      null,
      null,
      {
        "ALPHABET_SIZE": 26,
        "children": [
          {
            "ALPHABET_SIZE": 26,
            "children": [
              null,
              {
                "ALPHABET_SIZE": 26,
                "children": [
                  {
                    "ALPHABET_SIZE": 26,
                    "children": [
                      null,
                      null,
                      null,
                      null,
                      null,
                      null,
                      null,
                      null,
                      null,
                      null,
                      null,
                      {
                        "ALPHABET_SIZE": 26,
                        "children": [
                          {
                            "ALPHABET_SIZE": 26,
                            "children": [
                              null,
                              null,
                              null,
                              null,
                              null,
                              null,
                              null,
                              null,
                              null,
                              null,
                              null,
                              null,
                              null,
                              null,
                              null,
                              null,
                              null,
                              null,
                              null,
                              null,
                              null,
                              null,
                              null,
                              null,
                              null,
                              null
                            ],
                            "isEndOfWord": true
                          },
                          null,
                          null,
                          null,
                          null,
                          null,
                          null,
                          null,
                          null,
                          null,
                          null,
                          null,
                          null,
                          null,
                          null,
                          null,
                          null,
                          null,
                          null,
                          null,
                          null,
                          null,
                          null,
                          null,
                          null,
                          null
                        ],
                        "isEndOfWord": false
                      },
                      null,
                      null,
                      null,
                      null,
                      null,
                      null,
                      null,
                      null,
                      null,
                      null,
                      null,
                      null,
                      null,
                      null
                    ],
                    "isEndOfWord": false
                  },
                  null,
                  null,
                  null,
                  null,
                  null,
                  null,
                  null,
                  {
                    "ALPHABET_SIZE": 26,
                    "children": [
                      null,
                      null,
                      null,
                      null,
                      null,
                      null,
                      null,
                      null,
                      null,
                      null,
                      null,
                      null,
                      null,
                      {
                        "ALPHABET_SIZE": 26,
                        "children": [
                          null,
                          null,
                          null,
                          null,
                          null,
                          null,
                          null,
                          null,
                          null,
                          null,
                          null,
                          null,
                          null,
                          null,
                          null,
                          null,
                          null,
                          null,
                          null,
                          null,
                          null,
                          null,
                          null,
                          null,
                          null,
                          null
                        ],
                        "isEndOfWord": true
                      },
                      null,
                      null,
                      null,
                      null,
                      null,
                      null,
                      null,
                      null,
                      null,
                      null,
                      null,
                      null
                    ],
                    "isEndOfWord": false
                  },
                  null,
                  null,
                  null,
                  null,
                  null,
                  null,
                  null,
                  null,
                  null,
                  null,
                  null,
                  null,
                  null,
                  null,
                  null,
                  null,
                  null
                ],
                "isEndOfWord": true
              },
              null,
              null,
              null,
              null,
              null,
              null,
              null,
              null,
              null,
              null,
              null,
              null,
              null,
              null,
              null,
              null,
              null,
              {
                "ALPHABET_SIZE": 26,
                "children": [
                  {
                    "ALPHABET_SIZE": 26,
                    "children": [
                      null,
                      null,
                      {
                        "ALPHABET_SIZE": 26,
                        "children": [
                          null,
                          null,
                          null,
                          null,
                          null,
                          null,
                          null,
                          null,
                          null,
                          null,
                          null,
                          {
                            "ALPHABET_SIZE": 26,
                            "children": [
                              null,
                              null,
                              null,
                              null,
                              null,
                              null,
                              null,
                              null,
                              null,
                              null,
                              null,
                              null,
                              null,
                              null,
                              null,
                              null,
                              null,
                              null,
                              null,
                              null,
                              null,
                              null,
                              null,
                              null,
                              {
                                "ALPHABET_SIZE": 26,
                                "children": [
                                  null,
                                  null,
                                  null,
                                  null,
                                  null,
                                  null,
                                  null,
                                  null,
                                  null,
                                  null,
                                  null,
                                  null,
                                  null,
                                  null,
                                  null,
                                  null,
                                  null,
                                  null,
                                  {
                                    "ALPHABET_SIZE": 26,
                                    "children": [
                                      null,
                                      null,
                                      null,
                                      null,
                                      null,
                                      null,
                                      null,
                                      null,
                                      null,
                                      null,
                                      null,
                                      null,
                                      {
                                        "ALPHABET_SIZE": 26,
                                        "children": [
                                          null,
                                          null,
                                          null,
                                          null,
                                          null,
                                          null,
                                          null,
                                          null,
                                          null,
                                          null,
                                          null,
                                          null,
                                          null,
                                          null,
                                          null,
                                          null,
                                          null,
                                          null,
                                          null,
                                          null,
                                          null,
                                          null,
                                          null,
                                          null,
                                          null,
                                          null
                                        ],
                                        "isEndOfWord": true
                                      },
                                      null,
                                      null,
                                      null,
                                      null,
                                      null,
                                      null,
                                      null,
                                      null,
                                      null,
                                      null,
                                      null,
                                      null,
                                      null
                                    ],
                                    "isEndOfWord": false
                                  },
                                  null,
                                  null,
                                  null,
                                  null,
                                  null,
                                  null,
                                  null
                                ],
                                "isEndOfWord": false
                              },
                              null
                            ],
                            "isEndOfWord": false
                          },
                          null,
                          null,
                          null,
                          null,
                          null,
                          null,
                          null,
                          null,
                          null,
                          null,
                          null,
                          null,
                          null,
                          null
                        ],
                        "isEndOfWord": false
                      },
                      null,
                      null,
                      null,
                      null,
                      null,
                      null,
                      null,
                      null,
                      null,
                      null,
                      null,
                      null,
                      null,
                      null,
                      null,
                      null,
                      null,
                      null,
                      null,
                      null,
                      null,
                      null,
                      null
                    ],
                    "isEndOfWord": false
                  },
                  null,
                  null,
                  null,
                  {
                    "ALPHABET_SIZE": 26,
                    "children": [
                      null,
                      null,
                      null,
                      null,
                      null,
                      null,
                      {
                        "ALPHABET_SIZE": 26,
                        "children": [
                          null,
                          null,
                          null,
                          null,
                          null,
                          null,
                          null,
                          null,
                          null,
                          null,
                          null,
                          null,
                          null,
                          null,
                          {
                            "ALPHABET_SIZE": 26,
                            "children": [
                              null,
                              null,
                              null,
                              null,
                              null,
                              null,
                              null,
                              null,
                              null,
                              null,
                              null,
                              null,
                              null,
                              null,
                              null,
                              null,
                              null,
                              {
                                "ALPHABET_SIZE": 26,
                                "children": [
                                  null,
                                  null,
                                  null,
                                  null,
                                  null,
                                  null,
                                  null,
                                  null,
                                  null,
                                  null,
                                  null,
                                  null,
                                  null,
                                  null,
                                  null,
                                  null,
                                  null,
                                  null,
                                  null,
                                  null,
                                  null,
                                  null,
                                  null,
                                  null,
                                  {
                                    "ALPHABET_SIZE": 26,
                                    "children": [
                                      null,
                                      null,
                                      null,
                                      null,
                                      null,
                                      null,
                                      null,
                                      null,
                                      null,
                                      null,
                                      null,
                                      null,
                                      null,
                                      null,
                                      null,
                                      null,
                                      null,
                                      null,
                                      null,
                                      null,
                                      null,
                                      null,
                                      null,
                                      null,
                                      null,
                                      null
                                    ],
                                    "isEndOfWord": true
                                  },
                                  null
                                ],
                                "isEndOfWord": false
                              },
                              null,
                              null,
                              null,
                              null,
                              null,
                              null,
                              null,
                              null
                            ],
                            "isEndOfWord": false
                          },
                          null,
                          null,
                          null,
                          null,
                          null,
                          null,
                          null,
                          null,
                          null,
                          null,
                          null
                        ],
                        "isEndOfWord": false
                      },
                      null,
                      null,
                      null,
                      null,
                      null,
                      null,
                      null,
                      null,
                      null,
                      null,
                      {
                        "ALPHABET_SIZE": 26,
                        "children": [
                          null,
                          null,
                          null,
                          null,
                          null,
                          null,
                          null,
                          null,
                          null,
                          null,
                          null,
                          null,
                          null,
                          null,
                          null,
                          {
                            "ALPHABET_SIZE": 26,
                            "children": [
                              null,
                              null,
                              null,
                              null,
                              null,
                              null,
                              null,
                              null,
                              {
                                "ALPHABET_SIZE": 26,
                                "children": [
                                  null,
                                  null,
                                  null,
                                  null,
                                  null,
                                  null,
                                  null,
                                  null,
                                  null,
                                  null,
                                  null,
                                  {
                                    "ALPHABET_SIZE": 26,
                                    "children": [
                                      null,
                                      null,
                                      null,
                                      null,
                                      null,
                                      null,
                                      null,
                                      null,
                                      null,
                                      null,
                                      null,
                                      {
                                        "ALPHABET_SIZE": 26,
                                        "children": [
                                          {
                                            "ALPHABET_SIZE": 26,
                                            "children": [
                                              null,
                                              null,
                                              null,
                                              null,
                                              null,
                                              null,
                                              null,
                                              null,
                                              null,
                                              null,
                                              null,
                                              null,
                                              null,
                                              null,
                                              null,
                                              null,
                                              null,
                                              {
                                                "ALPHABET_SIZE": 26,
                                                "children": [
                                                  null,
                                                  null,
                                                  null,
                                                  null,
                                                  null,
                                                  null,
                                                  null,
                                                  null,
                                                  null,
                                                  null,
                                                  null,
                                                  null,
                                                  null,
                                                  null,
                                                  null,
                                                  null,
                                                  null,
                                                  null,
                                                  null,
                                                  null,
                                                  null,
                                                  null,
                                                  null,
                                                  null,
                                                  null,
                                                  null
                                                ],
                                                "isEndOfWord": true
                                              },
                                              null,
                                              null,
                                              null,
                                              null,
                                              null,
                                              null,
                                              null,
                                              null
                                            ],
                                            "isEndOfWord": false
                                          },
                                          null,
                                          null,
                                          null,
                                          null,
                                          null,
                                          null,
                                          null,
                                          null,
                                          null,
                                          null,
                                          null,
                                          null,
                                          null,
                                          null,
                                          null,
                                          null,
                                          null,
                                          null,
                                          null,
                                          null,
                                          null,
                                          null,
                                          null,
                                          null,
                                          null
                                        ],
                                        "isEndOfWord": false
                                      },
                                      null,
                                      null,
                                      null,
                                      null,
                                      null,
                                      null,
                                      null,
                                      null,
                                      null,
                                      null,
                                      null,
                                      null,
                                      null,
                                      null
                                    ],
                                    "isEndOfWord": false
                                  },
                                  null,
                                  null,
                                  null,
                                  null,
                                  null,
                                  null,
                                  null,
                                  null,
                                  null,
                                  null,
                                  null,
                                  null,
                                  null,
                                  null
                                ],
                                "isEndOfWord": false
                              },
                              null,
                              null,
                              null,
                              null,
                              null,
                              null,
                              null,
                              null,
                              null,
                              null,
                              null,
                              null,
                              null,
                              null,
                              null,
                              null,
                              null
                            ],
                            "isEndOfWord": false
                          },
                          null,
                          null,
                          null,
                          null,
                          null,
                          null,
                          null,
                          null,
                          null,
                          null
                        ],
                        "isEndOfWord": false
                      },
                      null,
                      null,
                      null,
                      null,
                      null,
                      null,
                      null,
                      null
                    ],
                    "isEndOfWord": false
                  },
                  null,
                  null,
                  {
                    "ALPHABET_SIZE": 26,
                    "children": [
                      {
                        "ALPHABET_SIZE": 26,
                        "children": [
                          null,
                          null,
                          null,
                          null,
                          null,
                          null,
                          null,
                          null,
                          null,
                          null,
                          null,
                          null,
                          null,
                          null,
                          null,
                          null,
                          null,
                          {
                            "ALPHABET_SIZE": 26,
                            "children": [
                              null,
                              null,
                              null,
                              null,
                              null,
                              null,
                              null,
                              null,
                              null,
                              null,
                              null,
                              null,
                              null,
                              null,
                              null,
                              null,
                              null,
                              null,
                              {
                                "ALPHABET_SIZE": 26,
                                "children": [
                                  null,
                                  null,
                                  null,
                                  null,
                                  null,
                                  null,
                                  null,
                                  null,
                                  {
                                    "ALPHABET_SIZE": 26,
                                    "children": [
                                      null,
                                      null,
                                      null,
                                      null,
                                      null,
                                      null,
                                      null,
                                      null,
                                      null,
                                      null,
                                      null,
                                      null,
                                      null,
                                      null,
                                      null,
                                      null,
                                      null,
                                      null,
                                      {
                                        "ALPHABET_SIZE": 26,
                                        "children": [
                                          null,
                                          null,
                                          null,
                                          null,
                                          null,
                                          null,
                                          null,
                                          null,
                                          null,
                                          null,
                                          null,
                                          null,
                                          null,
                                          null,
                                          null,
                                          null,
                                          null,
                                          null,
                                          null,
                                          null,
                                          null,
                                          null,
                                          null,
                                          null,
                                          null,
                                          null
                                        ],
                                        "isEndOfWord": true
                                      },
                                      null,
                                      null,
                                      null,
                                      null,
                                      null,
                                      null,
                                      null
                                    ],
                                    "isEndOfWord": false
                                  },
                                  null,
                                  null,
                                  null,
                                  null,
                                  null,
                                  null,
                                  null,
                                  null,
                                  null,
                                  null,
                                  null,
                                  null,
                                  null,
                                  null,
                                  null,
                                  null,
                                  null
                                ],
                                "isEndOfWord": false
                              },
                              null,
                              null,
                              null,
                              null,
                              null,
                              null,
                              null
                            ],
                            "isEndOfWord": false
                          },
                          null,
                          null,
                          null,
                          null,
                          null,
                          null,
                          null,
                          null
                        ],
                        "isEndOfWord": false
                      },
                      null,
                      null,
                      null,
                      null,
                      null,
                      null,
                      null,
                      null,
                      null,
                      null,
                      null,
                      null,
                      null,
                      null,
                      null,
                      null,
                      null,
                      null,
                      null,
                      null,
                      null,
                      null,
                      null,
                      null,
                      null
                    ],
                    "isEndOfWord": false
                  },
                  null,
                  null,
                  null,
                  null,
                  null,
                  null,
                  null,
                  null,
                  null,
                  null,
                  null,
                  null,
                  null,
                  null,
                  null,
                  null,
                  null,
                  null
                ],
                "isEndOfWord": false
              },
              null,
              null,
              null,
              null,
              null,
              null
            ],
            "isEndOfWord": false
          },
          null,
          null,
          null,
          {
            "ALPHABET_SIZE": 26,
            "children": [
              null,
              null,
              null,
              {
                "ALPHABET_SIZE": 26,
                "children": [
                  {
                    "ALPHABET_SIZE": 26,
                    "children": [
                      null,
                      null,
                      null,
                      null,
                      null,
                      null,
                      null,
                      null,
                      null,
                      null,
                      null,
                      null,
                      null,
                      null,
                      null,
                      null,
                      null,
                      {
                        "ALPHABET_SIZE": 26,
                        "children": [
                          null,
                          null,
                          null,
                          null,
                          null,
                          null,
                          null,
                          null,
                          null,
                          null,
                          null,
                          null,
                          null,
                          null,
                          null,
                          null,
                          null,
                          null,
                          null,
                          null,
                          null,
                          null,
                          null,
                          null,
                          null,
                          null
                        ],
                        "isEndOfWord": true
                      },
                      null,
                      null,
                      null,
                      null,
                      null,
                      null,
                      null,
                      null
                    ],
                    "isEndOfWord": false
                  },
                  null,
                  null,
                  null,
                  null,
                  null,
                  null,
                  null,
                  null,
                  null,
                  null,
                  null,
                  null,
                  null,
                  null,
                  null,
                  null,
                  null,
                  null,
                  null,
                  null,
                  null,
                  null,
                  null,
                  null,
                  null
                ],
                "isEndOfWord": false
              },
              null,
              null,
              null,
              null,
              null,
              null,
              null,
              {
                "ALPHABET_SIZE": 26,
                "children": [
                  null,
                  null,
                  null,
                  null,
                  null,
                  null,
                  null,
                  null,
                  null,
                  null,
                  null,
                  {
                    "ALPHABET_SIZE": 26,
                    "children": [
                      null,
                      null,
                      null,
                      null,
                      null,
                      null,
                      null,
                      null,
                      null,
                      null,
                      null,
                      null,
                      null,
                      null,
                      null,
                      null,
                      null,
                      null,
                      null,
                      null,
                      null,
                      null,
                      null,
                      null,
                      null,
                      null
                    ],
                    "isEndOfWord": true
                  },
                  null,
                  null,
                  null,
                  null,
                  null,
                  null,
                  null,
                  null,
                  null,
                  null,
                  null,
                  null,
                  null,
                  null
                ],
                "isEndOfWord": false
              },
              null,
              null,
              null,
              null,
              null,
              null,
              null,
              null,
              null,
              null,
              null,
              null,
              null,
              null
            ],
            "isEndOfWord": false
          },
          null,
          null,
          {
            "ALPHABET_SIZE": 26,
            "children": [
              null,
              null,
              null,
              null,
              null,
              null,
              null,
              null,
              null,
              null,
              null,
              null,
              null,
              null,
              null,
              null,
              null,
              {
                "ALPHABET_SIZE": 26,
                "children": [
                  null,
                  null,
                  null,
                  null,
                  null,
                  null,
                  null,
                  null,
                  null,
                  null,
                  null,
                  null,
                  null,
                  null,
                  {
                    "ALPHABET_SIZE": 26,
                    "children": [
                      null,
                      null,
                      null,
                      null,
                      null,
                      null,
                      null,
                      null,
                      null,
                      null,
                      null,
                      null,
                      null,
                      {
                        "ALPHABET_SIZE": 26,
                        "children": [
                          null,
                          null,
                          null,
                          null,
                          null,
                          null,
                          null,
                          null,
                          {
                            "ALPHABET_SIZE": 26,
                            "children": [
                              null,
                              null,
                              {
                                "ALPHABET_SIZE": 26,
                                "children": [
                                  null,
                                  null,
                                  null,
                                  null,
                                  null,
                                  null,
                                  null,
                                  null,
                                  null,
                                  null,
                                  null,
                                  null,
                                  null,
                                  null,
                                  null,
                                  null,
                                  null,
                                  null,
                                  null,
                                  null,
                                  null,
                                  null,
                                  null,
                                  null,
                                  null,
                                  null
                                ],
                                "isEndOfWord": true
                              },
                              null,
                              null,
                              null,
                              null,
                              null,
                              null,
                              null,
                              null,
                              null,
                              null,
                              null,
                              null,
                              null,
                              null,
                              null,
                              null,
                              null,
                              null,
                              null,
                              null,
                              null,
                              null,
                              null
                            ],
                            "isEndOfWord": false
                          },
                          null,
                          null,
                          null,
                          null,
                          null,
                          null,
                          null,
                          null,
                          null,
                          null,
                          null,
                          null,
                          null,
                          null,
                          null,
                          null,
                          null
                        ],
                        "isEndOfWord": false
                      },
                      null,
                      null,
                      null,
                      null,
                      null,
                      null,
                      null,
                      null,
                      null,
                      null,
                      null,
                      null
                    ],
                    "isEndOfWord": false
                  },
                  null,
                  null,
                  null,
                  null,
                  null,
                  null,
                  null,
                  null,
                  null,
                  null,
                  null
                ],
                "isEndOfWord": false
              },
              null,
              null,
              null,
              null,
              null,
              null,
              null,
              null
            ],
            "isEndOfWord": false
          },
          null,
          null,
          null,
          null,
          null,
          null,
          null,
          null,
          null,
          null,
          null,
          null,
          null,
          null,
          null,
          null,
          null,
          null
        ],
        "isEndOfWord": false
      },
      null,
      null,
      null,
      null,
      null,
      null,
      null,
      null,
      null,
      null,
      null,
      null,
      null,
      null,
      null,
      null,
      null,
      null,
      null,
      null,
      null,
      null,
      null
    ],
    "isEndOfWord": false
  }
}